README.md
setup.py
sammaNLP/__init__.py
sammaNLP/hj.py
sammaNLP.egg-info/PKG-INFO
sammaNLP.egg-info/SOURCES.txt
sammaNLP.egg-info/dependency_links.txt
sammaNLP.egg-info/requires.txt
sammaNLP.egg-info/top_level.txt
sammaNLP/callback/__init__.py
sammaNLP/callback/adversarial.py
sammaNLP/callback/lr_finder.py
sammaNLP/callback/lr_scheduler.py
sammaNLP/callback/modelcheckpoint.py
sammaNLP/callback/progressbar.py
sammaNLP/callback/trainingmonitor.py
sammaNLP/callback/optimizater/__init__.py
sammaNLP/callback/optimizater/adabound.py
sammaNLP/callback/optimizater/adafactor.py
sammaNLP/callback/optimizater/adamw.py
sammaNLP/callback/optimizater/lamb.py
sammaNLP/callback/optimizater/lars.py
sammaNLP/callback/optimizater/lookahead.py
sammaNLP/callback/optimizater/nadam.py
sammaNLP/callback/optimizater/novograd.py
sammaNLP/callback/optimizater/planradam.py
sammaNLP/callback/optimizater/radam.py
sammaNLP/callback/optimizater/ralamb.py
sammaNLP/callback/optimizater/ralars.py
sammaNLP/callback/optimizater/sgdw.py
sammaNLP/dataProcess/__init__.py
sammaNLP/dataProcess/readJson.py
sammaNLP/losses/__init__.py
sammaNLP/losses/dice_loss.py
sammaNLP/losses/focal_loss.py
sammaNLP/losses/label_smoothing.py
sammaNLP/metrics/__init__.py
sammaNLP/metrics/ner_metrics.py
sammaNLP/models/__init__.py
sammaNLP/models/albert_for_ner.py
sammaNLP/models/bert_for_ner.py
sammaNLP/models/layers/__init__.py
sammaNLP/models/layers/crf.py
sammaNLP/models/layers/linears.py
sammaNLP/models/transformers/__init__.py
sammaNLP/models/transformers/__main__.py
sammaNLP/models/transformers/configuration_albert.py
sammaNLP/models/transformers/configuration_auto.py
sammaNLP/models/transformers/configuration_bert.py
sammaNLP/models/transformers/configuration_ctrl.py
sammaNLP/models/transformers/configuration_distilbert.py
sammaNLP/models/transformers/configuration_gpt2.py
sammaNLP/models/transformers/configuration_openai.py
sammaNLP/models/transformers/configuration_roberta.py
sammaNLP/models/transformers/configuration_transfo_xl.py
sammaNLP/models/transformers/configuration_utils.py
sammaNLP/models/transformers/configuration_xlm.py
