Metadata-Version: 1.0
Name: sammaNLP
Version: 2020.10.12.21.32.27
Summary: some common tool for nlp task
Home-page: http://baidu.com
Author: samma
Author-email: 13336502700@163.com
License: MIT
Platform: UNKNOWN
